lizahwliblove/__init__.py
lizahwliblove/ast_graph.py
lizahwliblove/fibonacci.py
lizahwliblove/main.py
lizahwliblove-0.0.1.dist-info/METADATA
lizahwliblove-0.0.1.dist-info/WHEEL
lizahwliblove-0.0.1.dist-info/top_level.txt
lizahwliblove-0.0.1.dist-info/RECORD
